rstr/__init__.py
rstr/client.py
rstr/exceptions.py
rstr/models.py
rstr_client-0.2.0.dist-info/LICENSE
rstr_client-0.2.0.dist-info/WHEEL
rstr_client-0.2.0.dist-info/METADATA
rstr_client-0.2.0.dist-info/RECORD
