Metadata-Version: 2.1
Name: rstr-client
Version: 0.2.0
Summary: A client for the rstr blob-store.
Home-page: https://github.com/giuppep/rstr-client
License: MIT
Keywords: blob store,rstr,client
Author: Giuseppe Papallo
Author-email: giuseppe@papallo.it
Requires-Python: >=3.7,<4.0
Classifier: License :: OSI Approved :: MIT License
Classifier: Programming Language :: Python :: 3
Classifier: Programming Language :: Python :: 3.10
Classifier: Programming Language :: Python :: 3.7
Classifier: Programming Language :: Python :: 3.8
Classifier: Programming Language :: Python :: 3.9
Requires-Dist: requests (>=2.25.1,<3.0.0)
Project-URL: Bug Tracker, https://github.com/giuppep/rstr-client/issues
Project-URL: Repository, https://github.com/giuppep/rstr-client
